swarm_squad_ep1/__init__.py
swarm_squad_ep1/config.py
swarm_squad_ep1/main.py
swarm_squad_ep1/utils.py
swarm_squad_ep1/visualization.py
swarm_squad_ep1/controllers/__init__.py
swarm_squad_ep1/controllers/base_controller.py
swarm_squad_ep1/controllers/behavior_controller.py
swarm_squad_ep1/controllers/controller_factory.py
swarm_squad_ep1/controllers/formation_controller.py
swarm_squad_ep1/controllers/llm_controller.py
swarm_squad_ep1/gui/__init__.py
swarm_squad_ep1/gui/formation_control_gui.py
swarm_squad_ep1/models/__init__.py
swarm_squad_ep1/models/swarm_state.py
swarm_squad_ep1/tests/__init__.py
swarm_squad_ep1/tests/test_ollama.py
swarm_squad_ep1-0.2.3.dist-info/METADATA
swarm_squad_ep1-0.2.3.dist-info/WHEEL
swarm_squad_ep1-0.2.3.dist-info/entry_points.txt
swarm_squad_ep1-0.2.3.dist-info/licenses/LICENSE
swarm_squad_ep1-0.2.3.dist-info/RECORD
