Metadata-Version: 2.4
Name: swarm-squad-ep1
Version: 0.2.3
Summary: Swarm Squad Ep1: Surviving the jam
Project-URL: Homepage, https://swarm-squad.com
Project-URL: Documentation, https://docs.swarm-squad.com
Project-URL: Repository, https://github.com/Swarm-Squad/Swarm-Squad-Ep1
Author-email: Sang Buster <hello@singsongaftermath.com>
License: MIT License
License-File: LICENSE
Requires-Python: >=3.10
Requires-Dist: matplotlib>=3.10.1
Requires-Dist: pyqt5>=5.15.11
Requires-Dist: pytest>=8.3.5
Requires-Dist: requests>=2.32.3
